goal_jupyter_kernel/__init__.py
goal_jupyter_kernel/__main__.py
goal_jupyter_kernel/kernel.py
goal_jupyter_kernel-0.1.0.data/data/share/jupyter/kernels/goal/kernel.json
goal_jupyter_kernel-0.1.0.dist-info/METADATA
goal_jupyter_kernel-0.1.0.dist-info/WHEEL
goal_jupyter_kernel-0.1.0.dist-info/licenses/LICENSE
goal_jupyter_kernel-0.1.0.dist-info/RECORD
