Metadata-Version: 2.4
Name: goal_jupyter_kernel
Version: 0.1.0
Summary: Jupyter kernel for the Goal array programming language
Project-URL: Homepage, https://github.com/semperos/goal_jupyter_kernel
Author-email: Daniel Gregoire <daniel.l.gregoire@gmail.com>
License: Copyright 2024 Daniel Gregoire
License-File: LICENSE
Classifier: Intended Audience :: Developers
Classifier: License :: OSI Approved :: MIT License
Classifier: Programming Language :: Python :: 3
Requires-Python: >=3.8
Requires-Dist: ipykernel
Requires-Dist: jupyter-client
Requires-Dist: pexpect>=4.9.0
Provides-Extra: test
Requires-Dist: jupyter-kernel-test; extra == 'test'
